{
  "formatVersion": 1,
  "database": {
    "version": 1,
    "identityHash": "defabec740b473f5e268b04862328ade",
    "entities": [
      {
        "tableName": "Picture",
        "createSql": "CREATE TABLE IF NOT EXISTS `${TABLE_NAME}` ()",
        "fields": [],
        "primaryKey": {
          "autoGenerate": false,
          "columnNames": []
        },
        "indices": [],
        "foreignKeys": []
      }
    ],
    "views": [],
    "setupQueries": [
      "CREATE TABLE IF NOT EXISTS room_master_table (id INTEGER PRIMARY KEY,identity_hash TEXT)",
      "INSERT OR REPLACE INTO room_master_table (id,identity_hash) VALUES(42, 'defabec740b473f5e268b04862328ade')"
    ]
  }
}